fststr/__init__.py
fststr/fststr.py
fststr/test_fsa.py
fststr-0.5.data/scripts/applyfst.py
fststr-0.5.dist-info/LICENSE
fststr-0.5.dist-info/METADATA
fststr-0.5.dist-info/WHEEL
fststr-0.5.dist-info/top_level.txt
fststr-0.5.dist-info/RECORD
