Metadata-Version: 2.1
Name: fststr
Version: 0.5
Summary: UNKNOWN
Home-page: UNKNOWN
License: MIT license
Platform: UNKNOWN
License-File: LICENSE
